tests/unittests/__init__.py
tests/unittests/test_xcam.py
xcam/QuickUsb.py
xcam/__init__.py
xcam/cli.py
xcam/xcam.py
xcam-0.1.0.dist-info/DESCRIPTION.rst
xcam-0.1.0.dist-info/METADATA
xcam-0.1.0.dist-info/RECORD
xcam-0.1.0.dist-info/WHEEL
xcam-0.1.0.dist-info/entry_points.txt
xcam-0.1.0.dist-info/metadata.json
xcam-0.1.0.dist-info/top_level.txt
